{
    "key": "group_64147e1831669",
    "title": "__Block Popup slider",
    "fields": [
        {
            "key": "field_64147fce5f9b2",
            "label": "Popup slider",
            "name": "",
            "type": "accordion",
            "instructions": "",
            "required": 0,
            "conditional_logic": 0,
            "wrapper": {
                "width": "",
                "class": "",
                "id": ""
            },
            "open": 0,
            "multi_expand": 0,
            "endpoint": 0
        },
        {
            "key": "field_64147fe75f9b3",
            "label": "Choose media",
            "name": "_choose_media",
            "type": "radio",
            "instructions": "",
            "required": 0,
            "conditional_logic": 0,
            "wrapper": {
                "width": "",
                "class": "",
                "id": ""
            },
            "choices": {
                "from_our_work": "From our work block",
                "from_custom_media": "From Custom media"
            },
            "allow_null": 0,
            "other_choice": 0,
            "default_value": "",
            "layout": "vertical",
            "return_format": "value",
            "save_other_choice": 0
        },
        {
            "key": "field_64148111e43b7",
            "label": "media custom",
            "name": "_media_custom",
            "type": "gallery",
            "instructions": "",
            "required": 0,
            "conditional_logic": 0,
            "wrapper": {
                "width": "",
                "class": "",
                "id": ""
            },
            "return_format": "url",
            "preview_size": "full",
            "insert": "append",
            "library": "all",
            "min": "",
            "max": "",
            "min_width": "",
            "min_height": "",
            "min_size": "",
            "max_width": "",
            "max_height": "",
            "max_size": "",
            "mime_types": ""
        },
        {
            "key": "field_641482db64d9c",
            "label": "s",
            "name": "ss",
            "type": "flexible_content",
            "instructions": "",
            "required": 0,
            "conditional_logic": 0,
            "wrapper": {
                "width": "",
                "class": "",
                "id": ""
            },
            "layouts": {
                "layout_6414830302ee1": {
                    "key": "layout_6414830302ee1",
                    "name": "",
                    "label": "",
                    "display": "block",
                    "sub_fields": [],
                    "min": "",
                    "max": ""
                }
            },
            "button_label": "Add Row",
            "min": "",
            "max": ""
        }
    ],
    "location": [
        [
            {
                "param": "block",
                "operator": "==",
                "value": "acf\/popup-slider"
            }
        ]
    ],
    "menu_order": 0,
    "position": "normal",
    "style": "default",
    "label_placement": "top",
    "instruction_placement": "label",
    "hide_on_screen": "",
    "active": true,
    "description": "",
    "show_in_rest": 0,
    "modified": 1679065897
}